{"0": {"name": "Task 1", "desc": "Description 1", "haschildren": true, "children": [{"name": "Subtask 1", "desc": "Subdescription 1", "haschildren": false, "children": [], "checked": false, "completed": false, "duedate": [2025, 5, 24], "recurring": false}, {"name": "Subtask 3", "desc": "Subdescription 3", "haschildren": false, "children": [], "checked": false, "completed": false, "duedate": [2025, 5, 23], "recurring": false}], "checked": false, "completed": false, "duedate": [3000, 1, 1], "recurring": false}, "1": {"name": "New task", "desc": "New desc", "haschildren": false, "children": [], "checked": false, "completed": false, "duedate": [2025, 5, 30], "recurring": false}, "2": {"name": "test", "desc": "abd", "haschildren": false, "children": [], "checked": false, "completed": false, "duedate": [2025, 5, 26], "recurring": [2025, 5, 21, 4, 1]}}